arabaci01/EditWindow.py
arabaci01/GraphicsView.py
arabaci01/Marker.py
arabaci01/PseudoLabeller.py
arabaci01/Scene.py
arabaci01/__init__.py
arabaci01-0.0.2.dist-info/DESCRIPTION.rst
arabaci01-0.0.2.dist-info/METADATA
arabaci01-0.0.2.dist-info/RECORD
arabaci01-0.0.2.dist-info/WHEEL
arabaci01-0.0.2.dist-info/metadata.json
arabaci01-0.0.2.dist-info/top_level.txt
