Metadata-Version: 2.0
Name: arabaci01
Version: 0.0.2
Summary: A small example package
Home-page: https://github.com/Ahmet57/araba
Author: Example Author
Author-email: author@example.com
License: UNKNOWN
Platform: UNKNOWN
Classifier: Programming Language :: Python :: 3
Classifier: License :: OSI Approved :: MIT License
Classifier: Operating System :: OS Independent
Requires-Python: >=3.6
Requires-Dist: PySide2
Requires-Dist: numpy
Requires-Dist: qdarkstyle
Requires-Dist: torchvision
